sanymodel/__init__.py
sanymodel/_version.py
sanymodel/metaclass.py
sanymodel/modeltools.py
sanymodel/test.py
sanymodel/mpl_plotly/__init__.py
sanymodel/mpl_plotly/mpltools.py
sanymodel/mpl_plotly/renderer.py
sanymodel/mpl_plotly/mplexporter/__init__.py
sanymodel/mpl_plotly/mplexporter/_py3k_compat.py
sanymodel/mpl_plotly/mplexporter/exporter.py
sanymodel/mpl_plotly/mplexporter/tools.py
sanymodel/mpl_plotly/mplexporter/utils.py
sanymodel/mpl_plotly/mplexporter/renderers/__init__.py
sanymodel/mpl_plotly/mplexporter/renderers/base.py
sanymodel/mpl_plotly/mplexporter/renderers/fake_renderer.py
sanymodel/mpl_plotly/mplexporter/renderers/vega_renderer.py
sanymodel/mpl_plotly/mplexporter/renderers/vincent_renderer.py
sanymodel/test/__init__.py
sanymodel/test/test.py
test/__init__.py
test/test.py
sanymodel-0.3.3.dist-info/METADATA
sanymodel-0.3.3.dist-info/WHEEL
sanymodel-0.3.3.dist-info/top_level.txt
sanymodel-0.3.3.dist-info/RECORD
