Metadata-Version: 2.1
Name: sanymodel
Version: 0.3.3
Summary: tools for modeling and data processing
Home-page: http://gitlab.sanywind.net/sanydata/sanymodel
Author: zion
Author-email: Zion.Gao@foxmail.com
License: MIT Licence
Keywords: pip,sanymodel,Gao
Platform: any
Requires-Dist: sanydata
Requires-Dist: pandas
Requires-Dist: arrow
Requires-Dist: matplotlib (==3.1.3)
Requires-Dist: plotly (==5.1.0)
